wof_explorer/__init__.py
wof_explorer/base.py
wof_explorer/config.py
wof_explorer/factory.py
wof_explorer/py.typed
wof_explorer/types.py
wof_explorer/backends/__init__.py
wof_explorer/backends/sqlite/__init__.py
wof_explorer/backends/sqlite/connector.py
wof_explorer/backends/sqlite/models.py
wof_explorer/backends/sqlite/operations.py
wof_explorer/backends/sqlite/queries.py
wof_explorer/backends/sqlite/session.py
wof_explorer/backends/sqlite/tables.py
wof_explorer/discovery/__init__.py
wof_explorer/discovery/explorer.py
wof_explorer/display/__init__.py
wof_explorer/display/descriptor.py
wof_explorer/display/displays.py
wof_explorer/display/examples.py
wof_explorer/display/formatter.py
wof_explorer/display/progress.py
wof_explorer/display/styles.py
wof_explorer/display/table.py
wof_explorer/display/tree.py
wof_explorer/models/__init__.py
wof_explorer/models/filters.py
wof_explorer/models/geometry.py
wof_explorer/models/hierarchy.py
wof_explorer/models/places.py
wof_explorer/models/results.py
wof_explorer/processing/__init__.py
wof_explorer/processing/analysis.py
wof_explorer/processing/browser.py
wof_explorer/processing/collections.py
wof_explorer/processing/cursors.py
wof_explorer/processing/quick_explore.py
wof_explorer/processing/spatial.py
wof_explorer/processing/serializers/__init__.py
wof_explorer/processing/serializers/base.py
wof_explorer/processing/serializers/csv.py
wof_explorer/processing/serializers/geojson.py
wof_explorer/processing/serializers/wkt.py
wof_explorer/scripts/__init__.py
wof_explorer/scripts/downloader.py
wof_explorer/scripts/wof_explore.py
wof_explorer-0.5.0a2.dist-info/licenses/LICENSE
wof_explorer-0.5.0a2.dist-info/METADATA
wof_explorer-0.5.0a2.dist-info/WHEEL
wof_explorer-0.5.0a2.dist-info/entry_points.txt
wof_explorer-0.5.0a2.dist-info/top_level.txt
wof_explorer-0.5.0a2.dist-info/RECORD
