Metadata-Version: 2.4
Name: wof-explorer
Version: 0.5.0a2
Summary: WhosOnFirst geographic data explorer with cursor-based navigation and hierarchical queries
Author-email: Pattern Stack <hello@pattern-stack.com>
License: MIT License
Project-URL: Homepage, https://github.com/dugspi/wof-explorer
Project-URL: Repository, https://github.com/dugspi/wof-explorer
Project-URL: Documentation, https://github.com/dugspi/wof-explorer#readme
Project-URL: Issues, https://github.com/dugspi/wof-explorer/issues
Keywords: geospatial,whosonfirst,geography,sqlite,gis
Classifier: Development Status :: 3 - Alpha
Classifier: Intended Audience :: Developers
Classifier: License :: OSI Approved :: MIT License
Classifier: Programming Language :: Python :: 3
Classifier: Programming Language :: Python :: 3.9
Classifier: Programming Language :: Python :: 3.10
Classifier: Programming Language :: Python :: 3.11
Classifier: Programming Language :: Python :: 3.12
Classifier: Programming Language :: Python :: 3.13
Classifier: Topic :: Scientific/Engineering :: GIS
Classifier: Topic :: Database
Requires-Python: >=3.9
License-File: LICENSE
Requires-Dist: aiosqlite>=0.19.0
Requires-Dist: sqlalchemy>=2.0.0
Requires-Dist: pydantic>=2.0.0
Requires-Dist: greenlet>=2.0.0
Requires-Dist: typer>=0.19.1
Requires-Dist: rich>=13.0.0
Provides-Extra: dev
Requires-Dist: pytest>=7.4.0; extra == "dev"
Requires-Dist: pytest-asyncio>=0.21.0; extra == "dev"
Requires-Dist: mypy>=1.5.0; extra == "dev"
Requires-Dist: ruff>=0.1.0; extra == "dev"
Requires-Dist: black>=23.0.0; extra == "dev"
Provides-Extra: notebook
Requires-Dist: jupyter>=1.0.0; extra == "notebook"
Requires-Dist: ipython>=8.14.0; extra == "notebook"
Dynamic: license-file
